huaweicloudsdkidentitycenterstore/__init__.py
huaweicloudsdkidentitycenterstore/v1/__init__.py
huaweicloudsdkidentitycenterstore/v1/identitycenterstore_async_client.py
huaweicloudsdkidentitycenterstore/v1/identitycenterstore_client.py
huaweicloudsdkidentitycenterstore/v1/model/__init__.py
huaweicloudsdkidentitycenterstore/v1/model/address_dto.py
huaweicloudsdkidentitycenterstore/v1/model/alternate_identifier_dto.py
huaweicloudsdkidentitycenterstore/v1/model/attribute_operation_dto.py
huaweicloudsdkidentitycenterstore/v1/model/batch_delete_sessions_req_body.py
huaweicloudsdkidentitycenterstore/v1/model/batch_delete_sessions_request.py
huaweicloudsdkidentitycenterstore/v1/model/batch_delete_sessions_response.py
huaweicloudsdkidentitycenterstore/v1/model/batch_list_mfa_devices_for_user_req_body.py
huaweicloudsdkidentitycenterstore/v1/model/batch_list_mfa_devices_for_user_request.py
huaweicloudsdkidentitycenterstore/v1/model/batch_list_mfa_devices_for_user_response.py
huaweicloudsdkidentitycenterstore/v1/model/bearer_token.py
huaweicloudsdkidentitycenterstore/v1/model/create_bearer_token_request.py
huaweicloudsdkidentitycenterstore/v1/model/create_bearer_token_response.py
huaweicloudsdkidentitycenterstore/v1/model/create_external_id_p_configuration_for_directory_request.py
huaweicloudsdkidentitycenterstore/v1/model/create_external_id_p_configuration_for_directory_response.py
huaweicloudsdkidentitycenterstore/v1/model/create_group_membership_req_body.py
huaweicloudsdkidentitycenterstore/v1/model/create_group_membership_request.py
huaweicloudsdkidentitycenterstore/v1/model/create_group_membership_response.py
huaweicloudsdkidentitycenterstore/v1/model/create_group_req_body.py
huaweicloudsdkidentitycenterstore/v1/model/create_group_request.py
huaweicloudsdkidentitycenterstore/v1/model/create_group_response.py
huaweicloudsdkidentitycenterstore/v1/model/create_idp_req_body.py
huaweicloudsdkidentitycenterstore/v1/model/create_provisioning_tenant_request.py
huaweicloudsdkidentitycenterstore-3.1.184.dist-info/METADATA
huaweicloudsdkidentitycenterstore-3.1.184.dist-info/WHEEL
huaweicloudsdkidentitycenterstore-3.1.184.dist-info/licenses/LICENSE
huaweicloudsdkidentitycenterstore-3.1.184.dist-info/RECORD
